mikrotikapi/__init__.py
mikrotikapi/api_init.py
mikrotikapi/exceptions.py
mikrotikapi/routeros_requests.py
mikrotikapi/schemes/__init__.py
mikrotikapi/schemes/components/__init__.py
mikrotikapi/schemes/components/action.py
mikrotikapi/schemes/components/chain.py
mikrotikapi/schemes/components/dst_address.py
mikrotikapi/schemes/components/dst_addresses.py
mikrotikapi/schemes/components/protocol.py
mikrotikapi/schemes/components/src_address.py
mikrotikapi/schemes/components/src_addresses.py
mikrotikapi/schemes/components/to_addresses.py
mikrotikapi/schemes/components/to_ports.py
mikrotikapi/schemes/fields/__init__.py
mikrotikapi/schemes/fields/action.py
mikrotikapi/schemes/fields/bytes_field.py
mikrotikapi/schemes/fields/chain.py
mikrotikapi/schemes/fields/comment_field.py
mikrotikapi/schemes/fields/field_gen.py
mikrotikapi/schemes/fields/id_field.py
mikrotikapi/schemes/fields/in_interface.py
mikrotikapi/schemes/fields/in_interface_list.py
mikrotikapi/schemes/fields/log_prefix_field.py
mikrotikapi/schemes/fields/out_interface.py
mikrotikapi/schemes/fields/out_interface_list.py
mikrotikapi/schemes/fields/protocol.py
mikrotikapi/schemes/fields/routing_mark.py
mikrotikapi/schemes/fields/running_field.py
mikrotikapi/schemes/fields/to_ports.py
mikrotikapi/schemes/groups/__init__.py
mikrotikapi/schemes/groups/address_match_group.py
mikrotikapi/schemes/groups/interface_group.py
mikrotikapi/schemes/groups/interface_list_group.py
mikrotikapi/schemes/groups/mark_group.py
mikrotikapi/schemes/groups/mru_mtu_group.py
mikrotikapi/schemes/identity.py
mikrotikapi/schemes/l2tp_client.py
mikrotikapi/schemes/mangle.py
mikrotikapi/schemes/nat.py
mikrotikapi/schemes/profile.py
mikrotikapi/schemes/routing_tables.py
mikrotikapi/schemes/routing_tables_new.py
mikrotikapi/schemes/sercret.py
mikrotikapi/utils/__init__.py
mikrotikapi/utils/api_path.py
mikrotikapi/utils/balance_formatting.py
mikrotikapi/utils/get_objects_by_redis.py
mikrotikapi/utils/pluralize_word.py
mikrotikapi-0.4.2.dist-info/LICENSE.md
mikrotikapi-0.4.2.dist-info/METADATA
mikrotikapi-0.4.2.dist-info/WHEEL
mikrotikapi-0.4.2.dist-info/RECORD
