Metadata-Version: 2.1
Name: mikrotikapi
Version: 0.4.2
Summary: 
License: MIT
Author: goltsev
Author-email: mark@goltsev.net
Requires-Python: >=3.10,<4.0
Classifier: License :: OSI Approved :: MIT License
Classifier: Programming Language :: Python :: 3
Classifier: Programming Language :: Python :: 3.10
Classifier: Programming Language :: Python :: 3.11
Classifier: Programming Language :: Python :: 3.12
Requires-Dist: aiohttp (>=3.9.3,<4.0.0)
Requires-Dist: flake8 (>=7.0.0,<8.0.0)
Requires-Dist: pydantic (>=2.5.3,<=2.6.2)
Requires-Dist: requests (>=2.31.0,<3.0.0)
Requires-Dist: requests-toolbelt (>=1.0.0,<2.0.0)
